isort_vertical_alignment_plugin/__init__.py
isort_vertical_alignment_plugin/format.py
isort_vertical_alignment_plugin-0.0.1.dist-info/LICENSE
isort_vertical_alignment_plugin-0.0.1.dist-info/METADATA
isort_vertical_alignment_plugin-0.0.1.dist-info/WHEEL
isort_vertical_alignment_plugin-0.0.1.dist-info/entry_points.txt
isort_vertical_alignment_plugin-0.0.1.dist-info/top_level.txt
isort_vertical_alignment_plugin-0.0.1.dist-info/RECORD
